CHANGES.txt
MANIFEST.in
README.txt
development.ini
production.ini
setup.cfg
setup.py
MokaCMS.egg-info/PKG-INFO
MokaCMS.egg-info/SOURCES.txt
MokaCMS.egg-info/dependency_links.txt
MokaCMS.egg-info/entry_points.txt
MokaCMS.egg-info/not-zip-safe
MokaCMS.egg-info/requires.txt
MokaCMS.egg-info/top_level.txt
mokacms/__init__.py
mokacms/tests.py
mokacms/views.py
mokacms/static/favicon.ico
mokacms/static/footerbg.png
mokacms/static/headerbg.png
mokacms/static/ie6.css
mokacms/static/middlebg.png
mokacms/static/pylons.css
mokacms/static/pyramid-small.png
mokacms/static/pyramid.png
mokacms/static/transparent.gif
mokacms/templates/mytemplate.pt