Metadata-Version: 1.1
Name: MokaCMS
Version: 0.1dev
Summary: MokaCMS
Home-page: https://github.com/asidev/MokaCMS
Author: Asidev S.r.l.
Author-email: info@asidev.com
License: UNKNOWN
Keywords: web pyramid
Platform: UNKNOWN
Classifier: Development Status :: 2 - Pre-Alpha
Classifier: Programming Language :: Python
Classifier: Programming Language :: Python :: 3
Classifier: Framework :: Pyramid
Classifier: Topic :: Internet :: WWW/HTTP
Classifier: Topic :: Internet :: WWW/HTTP :: Dynamic Content
Classifier: Topic :: Internet :: WWW/HTTP :: WSGI :: Application
